frigga/__init__.py
frigga/__main__.py
frigga/client.py
frigga/config.py
frigga/frigga.py
frigga/grafana.py
frigga/prometheus.py
frigga/webserver.py
frigga/wsclient.py
frigga/wsserver.py
frigga-1.1.1.dist-info/LICENSE
frigga-1.1.1.dist-info/METADATA
frigga-1.1.1.dist-info/WHEEL
frigga-1.1.1.dist-info/entry_points.txt
frigga-1.1.1.dist-info/top_level.txt
frigga-1.1.1.dist-info/RECORD
