Metadata-Version: 2.1
Name: frigga
Version: 1.1.1
Summary: Scrape only relevant metrics in Prometheus, according to your Grafana dashboards
Home-page: https://github.com/unfor19/frigga
Author: Meir Gabay
Author-email: unfor19@gmail.com
License: MIT
Download-URL: https://github.com/unfor19/frigga/archive/1.1.1.tar.gz
Project-URL: Documentation, https://github.com/unfor19/frigga/wiki
Keywords: prometheus,grafana,dashboard,metrics,monitor,cloud,devops,cli
Platform: any
Classifier: Development Status :: 5 - Production/Stable
Classifier: Intended Audience :: Developers
Classifier: Topic :: Software Development :: Build Tools
Classifier: License :: OSI Approved :: MIT License
Classifier: Programming Language :: Python :: 3.6
Classifier: Programming Language :: Python :: 3.7
Classifier: Programming Language :: Python :: 3.8
Classifier: Programming Language :: Python :: 3.9
Classifier: Operating System :: POSIX :: Linux
Classifier: Operating System :: Unix
Classifier: Operating System :: MacOS
Classifier: Operating System :: Microsoft :: Windows
Requires-Python: ~=3.6
Requires-Dist: Click (>=7.1.1)
Requires-Dist: beautifulsoup4 (>=4.9.1)
Requires-Dist: Flask (>=1.1.2)
Requires-Dist: PyYAML (>=5.3.1)
Requires-Dist: requests (>=2.25.0)
Requires-Dist: waitress (>=1.4.4)
Requires-Dist: websockets (>=8.1)
